wiffi/__init__.py
wiffi-1.1.1.dist-info/LICENSE
wiffi-1.1.1.dist-info/METADATA
wiffi-1.1.1.dist-info/WHEEL
wiffi-1.1.1.dist-info/top_level.txt
wiffi-1.1.1.dist-info/RECORD
