Metadata-Version: 2.1
Name: wiffi
Version: 1.1.1
Summary: Python 3 package to interface devices from STALL WIFFI.
Home-page: https://github.com/mampfes/python-wiffi
Author: mampfes
Author-email: mampfes@users.noreply.github.com
License: MIT
Platform: UNKNOWN
Classifier: Programming Language :: Python :: 3
Classifier: License :: OSI Approved :: MIT License
Classifier: Operating System :: OS Independent
Requires-Python: >=3.6
License-File: LICENSE
